filterpy/__init__.py
filterpy/common/__init__.py
filterpy/common/discretization.py
filterpy/common/helpers.py
filterpy/common/kinematic.py
filterpy/common/tests/test_discretization.py
filterpy/common/tests/test_helpers.py
filterpy/discrete_bayes/__init__.py
filterpy/discrete_bayes/discrete_bayes.py
filterpy/discrete_bayes/tests/test_discrete_bayes.py
filterpy/examples/GetRadar.py
filterpy/examples/RadarUKF.py
filterpy/examples/__init__.py
filterpy/examples/bearing_only.py
filterpy/examples/radar_sim.py
filterpy/gh/__init__.py
filterpy/gh/gh_filter.py
filterpy/gh/tests/test_gh.py
filterpy/hinfinity/__init__.py
filterpy/hinfinity/hinfinity_filter.py
filterpy/hinfinity/tests/test_hinfinity.py
filterpy/kalman/CubatureKalmanFilter.py
filterpy/kalman/EKF.py
filterpy/kalman/IMM.py
filterpy/kalman/UKF.py
filterpy/kalman/__init__.py
filterpy/kalman/ensemble_kalman_filter.py
filterpy/kalman/fading_memory.py
filterpy/kalman/fixed_lag_smoother.py
filterpy/kalman/information_filter.py
filterpy/kalman/kalman_filter.py
filterpy/kalman/mmae.py
filterpy/kalman/sigma_points.py
filterpy/kalman/square_root.py
filterpy/kalman/unscented_transform.py
filterpy/kalman/tests/test_ckf.py
filterpy/kalman/tests/test_ekf.py
filterpy/kalman/tests/test_enkf.py
filterpy/kalman/tests/test_fls.py
filterpy/kalman/tests/test_fm.py
filterpy/kalman/tests/test_imm.py
filterpy/kalman/tests/test_information.py
filterpy/kalman/tests/test_kf.py
filterpy/kalman/tests/test_mmae.py
filterpy/kalman/tests/test_rts.py
filterpy/kalman/tests/test_sensor_fusion.py
filterpy/kalman/tests/test_sqrtkf.py
filterpy/kalman/tests/test_ukf.py
filterpy/kalman/tests/ukf2.py
filterpy/leastsq/__init__.py
filterpy/leastsq/least_squares.py
filterpy/leastsq/tests/test_lsq.py
filterpy/memory/__init__.py
filterpy/memory/fading_memory.py
filterpy/memory/tests/test_fading_memory.py
filterpy/monte_carlo/__init__.py
filterpy/monte_carlo/resampling.py
filterpy/stats/__init__.py
filterpy/stats/stats.py
filterpy/stats/tests/test_stats.py
roger_filters-0.2.0.dist-info/licenses/LICENSE
roger_filters-0.2.0.dist-info/METADATA
roger_filters-0.2.0.dist-info/WHEEL
roger_filters-0.2.0.dist-info/top_level.txt
roger_filters-0.2.0.dist-info/RECORD
