Metadata-Version: 2.4
Name: roger-filters
Version: 0.2.0
Summary: Add your description here
Requires-Python: >=3.13
License-File: LICENSE
Requires-Dist: matplotlib>=3.10.1
Requires-Dist: scipy>=1.15.2
Dynamic: license-file
